tidbcloudy/__init__.py
tidbcloudy/_base.py
tidbcloudy/backup.py
tidbcloudy/cluster.py
tidbcloudy/context.py
tidbcloudy/exception.py
tidbcloudy/project.py
tidbcloudy/restore.py
tidbcloudy/specification.py
tidbcloudy/tidbcloud.py
tidbcloudy/util/ip.py
tidbcloudy/util/log.py
tidbcloudy/util/page.py
tidbcloudy/util/timestamp.py
tidbcloudy-1.1.1.dist-info/LICENSE
tidbcloudy-1.1.1.dist-info/METADATA
tidbcloudy-1.1.1.dist-info/WHEEL
tidbcloudy-1.1.1.dist-info/RECORD
