Metadata-Version: 2.1
Name: tidbcloudy
Version: 1.1.1
Summary: (Unofficial) Python SDK for TiDB Cloud
Home-page: https://github.com/Oreoxmt/tidbcloudy
Author: Aolin
Author-email: aolinz@outlook.com
Requires-Python: >=3.7,<4.0
Classifier: Programming Language :: Python :: 3
Classifier: Programming Language :: Python :: 3.7
Classifier: Programming Language :: Python :: 3.8
Classifier: Programming Language :: Python :: 3.9
Classifier: Programming Language :: Python :: 3.10
Classifier: Programming Language :: Python :: 3.11
Requires-Dist: deprecation (>=2.1.0,<3.0.0)
Requires-Dist: httpx (>=0.24.1,<0.25.0)
Requires-Dist: mysqlclient (>=2.1.1,<3.0.0)
Project-URL: Documentation, https://github.com/Oreoxmt/tidbcloudy#readme
Project-URL: Repository, https://github.com/Oreoxmt/tidbcloudy
